power01_min/__init__.py
power01_min/min.py
power01_min-0.1.2.dist-info/METADATA
power01_min-0.1.2.dist-info/WHEEL
power01_min-0.1.2.dist-info/entry_points.txt
power01_min-0.1.2.dist-info/top_level.txt
power01_min-0.1.2.dist-info/RECORD
