Metadata-Version: 2.1
Name: power01_min
Version: 0.1.2
Summary: Default template for PDM package
Author-email: baechu805 <bjoo606@naver.com>
License: MIT
Requires-Python: >=3.9
